flyconsole/__init__.py
flyconsole/console.py
flyconsole/input.py
flyconsole-1.2.dist-info/LICENSE
flyconsole-1.2.dist-info/METADATA
flyconsole-1.2.dist-info/WHEEL
flyconsole-1.2.dist-info/top_level.txt
flyconsole-1.2.dist-info/RECORD
