Metadata-Version: 2.1
Name: flyconsole
Version: 1.2
Summary: Modify the Terminal
Author: fluffy
Project-URL: Homepage, https://github.com/fluffeliger/fly-console
Project-URL: Issues, https://github.com/fluffeliger/fly-console/issues
Classifier: Programming Language :: Python :: 3
Classifier: License :: OSI Approved :: MIT License
Classifier: Operating System :: OS Independent
Requires-Python: >=3.8
License-File: LICENSE
Provides-Extra: pdf
Requires-Dist: msvcrt ; extra == 'pdf'
Requires-Dist: tty ; extra == 'pdf'
